SEM-2/intro-hdl/Lab-1 (cswap)/cswap_fa.v

module cswap(A1, B1, C1, A, B, C);
    output A1, B1, C1;
    input A, B, C;

    wire Ab, B11, B12, C11, C12;
    buf (A1, A);
    not (Ab, A);
    and (B11, Ab, B);
    and (B12, A, C);
    or (B1, B11, B12);
    and (C11, Ab, C);
    and (C12, A, B);
    or (C1, C11, C12);

endmodule

module cswap_fa(s, cout, a, b, cin);
    output s, cout;
    input a, b, cin;
    
    //see https://en.wikipedia.org/wiki/File:Full_Adder_using_reversible_Fredkin_gates.svg
    wire i1, i2, i3;
    wire j1, j2, j3;
    wire k1, k2, k3;
    wire l1, l2, l3;
    wire m1, m2, m3;
    cswap g1(i1, i2, i3, a, 1'b0, 1'b1);
    cswap g2(j1, j2, j3, b, i2, i3);
    cswap g3(k1, k2, k3, cin, j2, j3);
    cswap g4(s, l2, l3, k2, k1, k3);
    cswap g5(m1, cout, m3, j1, l2, l3);

endmodule

SEM-2/intro-hdl/Lab-1 (cswap)/cswap_fa_tb.v
`timescale 1 ns / 1 ps

module test;
  /* Make A, B, C three clocks so all combination are tested */
  reg A=0;
  always #4 A = !A;
  reg B=0;
  always #2 B = !B;
  reg C=0;
  always #1 C = !C;

  wire A1, B1, C1;
  //cswap c1 (A1, B1, C1, A, B, C);
  //cswap c1 (A1.(A1), .B1(B1), .C1(C1), .A(A), .B(B), .C(C));
  cswap_fa fa1(A1, B1, A, B, C);

  initial
    begin
        $monitor("At time %t, %0d %0d %0d %0d %0d %0d", $time, A1, B1, C1, A, B, C);
        #100 $finish;
    end
  initial
    begin
        $dumpfile("fa.vcd"); 
        $dumpvars;
    end 
endmodule // test

SEM-2/intro-hdl/Lab-1 (cswap)/fa.vcd
$date
	Wed Apr 24 21:34:45 2019
$end
$version
	Icarus Verilog
$end
$timescale
	1ps
$end
$scope module test $end
$var wire 1 ! C1 $end
$var wire 1 " B1 $end
$var wire 1 # A1 $end
$var reg 1 $ A $end
$var reg 1 % B $end
$var reg 1 & C $end
$scope module fa1 $end
$var wire 1 $ a $end
$var wire 1 % b $end
$var wire 1 & cin $end
$var wire 1 # s $end
$var wire 1 ' m3 $end
$var wire 1 ( m1 $end
$var wire 1 ) l3 $end
$var wire 1 * l2 $end
$var wire 1 + k3 $end
$var wire 1 , k2 $end
$var wire 1 - k1 $end
$var wire 1 . j3 $end
$var wire 1 / j2 $end
$var wire 1 0 j1 $end
$var wire 1 1 i3 $end
$var wire 1 2 i2 $end
$var wire 1 3 i1 $end
$var wire 1 " cout $end
$scope module g1 $end
$var wire 1 $ A $end
$var wire 1 3 A1 $end
$var wire 1 4 Ab $end
$var wire 1 5 B $end
$var wire 1 2 B1 $end
$var wire 1 6 B11 $end
$var wire 1 7 B12 $end
$var wire 1 8 C $end
$var wire 1 1 C1 $end
$var wire 1 9 C11 $end
$var wire 1 : C12 $end
$upscope $end
$scope module g2 $end
$var wire 1 % A $end
$var wire 1 0 A1 $end
$var wire 1 ; Ab $end
$var wire 1 2 B $end
$var wire 1 / B1 $end
$var wire 1 < B11 $end
$var wire 1 = B12 $end
$var wire 1 1 C $end
$var wire 1 . C1 $end
$var wire 1 > C11 $end
$var wire 1 ? C12 $end
$upscope $end
$scope module g3 $end
$var wire 1 & A $end
$var wire 1 - A1 $end
$var wire 1 @ Ab $end
$var wire 1 / B $end
$var wire 1 , B1 $end
$var wire 1 A B11 $end
$var wire 1 B B12 $end
$var wire 1 . C $end
$var wire 1 + C1 $end
$var wire 1 C C11 $end
$var wire 1 D C12 $end
$upscope $end
$scope module g4 $end
$var wire 1 , A $end
$var wire 1 # A1 $end
$var wire 1 E Ab $end
$var wire 1 - B $end
$var wire 1 * B1 $end
$var wire 1 F B11 $end
$var wire 1 G B12 $end
$var wire 1 + C $end
$var wire 1 ) C1 $end
$var wire 1 H C11 $end
$var wire 1 I C12 $end
$upscope $end
$scope module g5 $end
$var wire 1 0 A $end
$var wire 1 ( A1 $end
$var wire 1 J Ab $end
$var wire 1 * B $end
$var wire 1 " B1 $end
$var wire 1 K B11 $end
$var wire 1 L B12 $end
$var wire 1 ) C $end
$var wire 1 ' C1 $end
$var wire 1 M C11 $end
$var wire 1 N C12 $end
$upscope $end
$upscope $end
$upscope $end
$enddefinitions $end
#0
$dumpvars
0N
1M
0L
0K
1J
0I
1H
0G
0F
1E
0D
1C
0B
0A
1@
0?
1>
0=
0<
1;
0:
19
18
07
06
05
14
03
02
11
00
0/
1.
0-
0,
1+
0*
1)
0(
1'
0&
0%
0$
0#
0"
z!
$end
#1000
0"
0K
0H
0*
0+
1#
0E
0G
0F
1I
0C
1,
1-
0@
1B
1&
#2000
0N
0*
0G
0H
0'
0)
0+
1#
0E
0M
0"
0.
0I
1A
0C
1,
1(
0J
0L
0>
1/
0-
1@
0B
10
0;
1=
0&
1%
#3000
1'
1"
1F
1H
1N
1L
0#
1E
1*
1)
0,
0G
0I
0A
1+
1-
0@
1D
1&
#4000
1#
0E
0G
1,
0)
1A
0C
0*
0H
0K
0M
0"
0'
0.
01
0F
0+
0(
1J
0L
0N
1<
0>
1/
09
12
0-
1@
0D
00
1;
0=
13
04
17
0&
0%
1$
#5000
1"
1'
1F
1H
1K
1M
0#
1E
1*
1)
0,
0G
0I
0A
1+
1-
0@
1D
1&
#6000
1"
0'
0#
1E
0G
1)
0*
0,
1H
0K
0M
0/
0F
0A
1C
1+
1(
0J
1L
0N
0<
1.
0-
1@
0D
10
0;
1?
0&
1%
#7000
0'
0N
0H
0*
0+
1#
0E
0G
0F
1I
0C
1,
1-
0@
1B
1&
#8000
1H
1+
1C
1'
1>
1)
0#
1E
1M
0"
11
0I
0,
0(
1J
0L
1.
19
02
0-
1@
0B
00
1;
0?
03
14
07
0&
0%
0$
#9000
0"
0K
0H
0*
0+
1#
0E
0G
0F
1I
0C
1,
1-
0@
1B
1&
#10000
0N
0*
0G
0H
0'
0)
0+
1#
0E
0M
0"
0.
0I
1A
0C
1,
1(
0J
0L
0>
1/
0-
1@
0B
10
0;
1=
0&
1%
#11000
1'
1"
1F
1H
1N
1L
0#
1E
1*
1)
0,
0G
0I
0A
1+
1-
0@
1D
1&
#12000
1#
0E
0G
1,
0)
1A
0C
0*
0H
0K
0M
0"
0'
0.
01
0F
0+
0(
1J
0L
0N
1<
0>
1/
09
12
0-
1@
0D
00
1;
0=
13
04
17
0&
0%
1$
#13000
1"
1'
1F
1H
1K
1M
0#
1E
1*
1)
0,
0G
0I
0A
1+
1-
0@
1D
1&
#14000
1"
0'
0#
1E
0G
1)
0*
0,
1H
0K
0M
0/
0F
0A
1C
1+
1(
0J
1L
0N
0<
1.
0-
1@
0D
10
0;
1?
0&
1%
#15000
0'
0N
0H
0*
0+
1#
0E
0G
0F
1I
0C
1,
1-
0@
1B
1&
#16000
1H
1+
1C
1'
1>
1)
0#
1E
1M
0"
11
0I
0,
0(
1J
0L
1.
19
02
0-
1@
0B
00
1;
0?
03
14
07
0&
0%
0$
#17000
0"
0K
0H
0*
0+
1#
0E
0G
0F
1I
0C
1,
1-
0@
1B
1&
#18000
0N
0*
0G
0H
0'
0)
0+
1#
0E
0M
0"
0.
0I
1A
0C
1,
1(
0J
0L
0>
1/
0-
1@
0B
10
0;
1=
0&
1%
#19000
1'
1"
1F
1H
1N
1L
0#
1E
1*
1)
0,
0G
0I
0A
1+
1-
0@
1D
1&
#20000
1#
0E
0G
1,
0)
1A
0C
0*
0H
0K
0M
0"
0'
0.
01
0F
0+
0(
1J
0L
0N
1<
0>
1/
09
12
0-
1@
0D
00
1;
0=
13
04
17
0&
0%
1$
#21000
1"
1'
1F
1H
1K
1M
0#
1E
1*
1)
0,
0G
0I
0A
1+
1-
0@
1D
1&
#22000
1"
0'
0#
1E
0G
1)
0*
0,
1H
0K
0M
0/
0F
0A
1C
1+
1(
0J
1L
0N
0<
1.
0-
1@
0D
10
0;
1?
0&
1%
#23000
0'
0N
0H
0*
0+
1#
0E
0G
0F
1I
0C
1,
1-
0@
1B
1&
#24000
1H
1+
1C
1'
1>
1)
0#
1E
1M
0"
11
0I
0,
0(
1J
0L
1.
19
02
0-
1@
0B
00
1;
0?
03
14
07
0&
0%
0$
#25000
0"
0K
0H
0*
0+
1#
0E
0G
0F
1I
0C
1,
1-
0@
1B
1&
#26000
0N
0*
0G
0H
0'
0)
0+
1#
0E
0M
0"
0.
0I
1A
0C
1,
1(
0J
0L
0>
1/
0-
1@
0B
10
0;
1=
0&
1%
#27000
1'
1"
1F
1H
1N
1L
0#
1E
1*
1)
0,
0G
0I
0A
1+
1-
0@
1D
1&
#28000
1#
0E
0G
1,
0)
1A
0C
0*
0H
0K
0M
0"
0'
0.
01
0F
0+
0(
1J
0L
0N
1<
0>
1/
09
12
0-
1@
0D
00
1;
0=
13
04
17
0&
0%
1$
#29000
1"
1'
1F
1H
1K
1M
0#
1E
1*
1)
0,
0G
0I
0A
1+
1-
0@
1D
1&
#30000
1"
0'
0#
1E
0G
1)
0*
0,
1H
0K
0M
0/
0F
0A
1C
1+
1(
0J
1L
0N
0<
1.
0-
1@
0D
10
0;
1?
0&
1%
#31000
0'
0N
0H
0*
0+
1#
0E
0G
0F
1I
0C
1,
1-
0@
1B
1&
#32000
1H
1+
1C
1'
1>
1)
0#
1E
1M
0"
11
0I
0,
0(
1J
0L
1.
19
02
0-
1@
0B
00
1;
0?
03
14
07
0&
0%
0$
#33000
0"
0K
0H
0*
0+
1#
0E
0G
0F
1I
0C
1,
1-
0@
1B
1&
#34000
0N
0*
0G
0H
0'
0)
0+
1#
0E
0M
0"
0.
0I
1A
0C
1,
1(
0J
0L
0>
1/
0-
1@
0B
10
0;
1=
0&
1%
#35000
1'
1"
1F
1H
1N
1L
0#
1E
1*
1)
0,
0G
0I
0A
1+
1-
0@
1D
1&
#36000
1#
0E
0G
1,
0)
1A
0C
0*
0H
0K
0M
0"
0'
0.
01
0F
0+
0(
1J
0L
0N
1<
0>
1/
09
12
0-
1@
0D
00
1;
0=
13
04
17
0&
0%
1$
#37000
1"
1'
1F
1H
1K
1M
0#
1E
1*
1)
0,
0G
0I
0A
1+
1-
0@
1D
1&
#38000
1"
0'
0#
1E
0G
1)
0*
0,
1H
0K
0M
0/
0F
0A
1C
1+
1(
0J
1L
0N
0<
1.
0-
1@
0D
10
0;
1?
0&
1%
#39000
0'
0N
0H
0*
0+
1#
0E
0G
0F
1I
0C
1,
1-
0@
1B
1&
#40000
1H
1+
1C
1'
1>
1)
0#
1E
1M
0"
11
0I
0,
0(
1J
0L
1.
19
02
0-
1@
0B
00
1;
0?
03
14
07
0&
0%
0$
#41000
0"
0K
0H
0*
0+
1#
0E
0G
0F
1I
0C
1,
1-
0@
1B
1&
#42000
0N
0*
0G
0H
0'
0)
0+
1#
0E
0M
0"
0.
0I
1A
0C
1,
1(
0J
0L
0>
1/
0-
1@
0B
10
0;
1=
0&
1%
#43000
1'
1"
1F
1H
1N
1L
0#
1E
1*
1)
0,
0G
0I
0A
1+
1-
0@
1D
1&
#44000
1#
0E
0G
1,
0)
1A
0C
0*
0H
0K
0M
0"
0'
0.
01
0F
0+
0(
1J
0L
0N
1<
0>
1/
09
12
0-
1@
0D
00
1;
0=
13
04
17
0&
0%
1$
#45000
1"
1'
1F
1H
1K
1M
0#
1E
1*
1)
0,
0G
0I
0A
1+
1-
0@
1D
1&
#46000
1"
0'
0#
1E
0G
1)
0*
0,
1H
0K
0M
0/
0F
0A
1C
1+
1(
0J
1L
0N
0<
1.
0-
1@
0D
10
0;
1?
0&
1%
#47000
0'
0N
0H
0*
0+
1#
0E
0G
0F
1I
0C
1,
1-
0@
1B
1&
#48000
1H
1+
1C
1'
1>
1)
0#
1E
1M
0"
11
0I
0,
0(
1J
0L
1.
19
02
0-
1@
0B
00
1;
0?
03
14
07
0&
0%
0$
#49000
0"
0K
0H
0*
0+
1#
0E
0G
0F
1I
0C
1,
1-
0@
1B
1&
#50000
0N
0*
0G
0H
0'
0)
0+
1#
0E
0M
0"
0.
0I
1A
0C
1,
1(
0J
0L
0>
1/
0-
1@
0B
10
0;
1=
0&
1%
#51000
1'
1"
1F
1H
1N
1L
0#
1E
1*
1)
0,
0G
0I
0A
1+
1-
0@
1D
1&
#52000
1#
0E
0G
1,
0)
1A
0C
0*
0H
0K
0M
0"
0'
0.
01
0F
0+
0(
1J
0L
0N
1<
0>
1/
09
12
0-
1@
0D
00
1;
0=
13
04
17
0&
0%
1$
#53000
1"
1'
1F
1H
1K
1M
0#
1E
1*
1)
0,
0G
0I
0A
1+
1-
0@
1D
1&
#54000
1"
0'
0#
1E
0G
1)
0*
0,
1H
0K
0M
0/
0F
0A
1C
1+
1(
0J
1L
0N
0<
1.
0-
1@
0D
10
0;
1?
0&
1%
#55000
0'
0N
0H
0*
0+
1#
0E
0G
0F
1I
0C
1,
1-
0@
1B
1&
#56000
1H
1+
1C
1'
1>
1)
0#
1E
1M
0"
11
0I
0,
0(
1J
0L
1.
19
02
0-
1@
0B
00
1;
0?
03
14
07
0&
0%
0$
#57000
0"
0K
0H
0*
0+
1#
0E
0G
0F
1I
0C
1,
1-
0@
1B
1&
#58000
0N
0*
0G
0H
0'
0)
0+
1#
0E
0M
0"
0.
0I
1A
0C
1,
1(
0J
0L
0>
1/
0-
1@
0B
10
0;
1=
0&
1%
#59000
1'
1"
1F
1H
1N
1L
0#
1E
1*
1)
0,
0G
0I
0A
1+
1-
0@
1D
1&
#60000
1#
0E
0G
1,
0)
1A
0C
0*
0H
0K
0M
0"
0'
0.
01
0F
0+
0(
1J
0L
0N
1<
0>
1/
09
12
0-
1@
0D
00
1;
0=
13
04
17
0&
0%
1$
#61000
1"
1'
1F
1H
1K
1M
0#
1E
1*
1)
0,
0G
0I
0A
1+
1-
0@
1D
1&
#62000
1"
0'
0#
1E
0G
1)
0*
0,
1H
0K
0M
0/
0F
0A
1C
1+
1(
0J
1L
0N
0<
1.
0-
1@
0D
10
0;
1?
0&
1%
#63000
0'
0N
0H
0*
0+
1#
0E
0G
0F
1I
0C
1,
1-
0@
1B
1&
#64000
1H
1+
1C
1'
1>
1)
0#
1E
1M
0"
11
0I
0,
0(
1J
0L
1.
19
02
0-
1@
0B
00
1;
0?
03
14
07
0&
0%
0$
#65000
0"
0K
0H
0*
0+
1#
0E
0G
0F
1I
0C
1,
1-
0@
1B
1&
#66000
0N
0*
0G
0H
0'
0)
0+
1#
0E
0M
0"
0.
0I
1A
0C
1,
1(
0J
0L
0>
1/
0-
1@
0B
10
0;
1=
0&
1%
#67000
1'
1"
1F
1H
1N
1L
0#
1E
1*
1)
0,
0G
0I
0A
1+
1-
0@
1D
1&
#68000
1#
0E
0G
1,
0)
1A
0C
0*
0H
0K
0M
0"
0'
0.
01
0F
0+
0(
1J
0L
0N
1<
0>
1/
09
12
0-
1@
0D
00
1;
0=
13
04
17
0&
0%
1$
#69000
1"
1'
1F
1H
1K
1M
0#
1E
1*
1)
0,
0G
0I
0A
1+
1-
0@
1D
1&
#70000
1"
0'
0#
1E
0G
1)
0*
0,
1H
0K
0M
0/
0F
0A
1C
1+
1(
0J
1L
0N
0<
1.
0-
1@
0D
10
0;
1?
0&
1%
#71000
0'
0N
0H
0*
0+
1#
0E
0G
0F
1I
0C
1,
1-
0@
1B
1&
#72000
1H
1+
1C
1'
1>
1)
0#
1E
1M
0"
11
0I
0,
0(
1J
0L
1.
19
02
0-
1@
0B
00
1;
0?
03
14
07
0&
0%
0$
#73000
0"
0K
0H
0*
0+
1#
0E
0G
0F
1I
0C
1,
1-
0@
1B
1&
#74000
0N
0*
0G
0H
0'
0)
0+
1#
0E
0M
0"
0.
0I
1A
0C
1,
1(
0J
0L
0>
1/
0-
1@
0B
10
0;
1=
0&
1%
#75000
1'
1"
1F
1H
1N
1L
0#
1E
1*
1)
0,
0G
0I
0A
1+
1-
0@
1D
1&
#76000
1#
0E
0G
1,
0)
1A
0C
0*
0H
0K
0M
0"
0'
0.
01
0F
0+
0(
1J
0L
0N
1<
0>
1/
09
12
0-
1@
0D
00
1;
0=
13
04
17
0&
0%
1$
#77000
1"
1'
1F
1H
1K
1M
0#
1E
1*
1)
0,
0G
0I
0A
1+
1-
0@
1D
1&
#78000
1"
0'
0#
1E
0G
1)
0*
0,
1H
0K
0M
0/
0F
0A
1C
1+
1(
0J
1L
0N
0<
1.
0-
1@
0D
10
0;
1?
0&
1%
#79000
0'
0N
0H
0*
0+
1#
0E
0G
0F
1I
0C
1,
1-
0@
1B
1&
#80000
1H
1+
1C
1'
1>
1)
0#
1E
1M
0"
11
0I
0,
0(
1J
0L
1.
19
02
0-
1@
0B
00
1;
0?
03
14
07
0&
0%
0$
#81000
0"
0K
0H
0*
0+
1#
0E
0G
0F
1I
0C
1,
1-
0@
1B
1&
#82000
0N
0*
0G
0H
0'
0)
0+
1#
0E
0M
0"
0.
0I
1A
0C
1,
1(
0J
0L
0>
1/
0-
1@
0B
10
0;
1=
0&
1%
#83000
1'
1"
1F
1H
1N
1L
0#
1E
1*
1)
0,
0G
0I
0A
1+
1-
0@
1D
1&
#84000
1#
0E
0G
1,
0)
1A
0C
0*
0H
0K
0M
0"
0'
0.
01
0F
0+
0(
1J
0L
0N
1<
0>
1/
09
12
0-
1@
0D
00
1;
0=
13
04
17
0&
0%
1$
#85000
1"
1'
1F
1H
1K
1M
0#
1E
1*
1)
0,
0G
0I
0A
1+
1-
0@
1D
1&
#86000
1"
0'
0#
1E
0G
1)
0*
0,
1H
0K
0M
0/
0F
0A
1C
1+
1(
0J
1L
0N
0<
1.
0-
1@
0D
10
0;
1?
0&
1%
#87000
0'
0N
0H
0*
0+
1#
0E
0G
0F
1I
0C
1,
1-
0@
1B
1&
#88000
1H
1+
1C
1'
1>
1)
0#
1E
1M
0"
11
0I
0,
0(
1J
0L
1.
19
02
0-
1@
0B
00
1;
0?
03
14
07
0&
0%
0$
#89000
0"
0K
0H
0*
0+
1#
0E
0G
0F
1I
0C
1,
1-
0@
1B
1&
#90000
0N
0*
0G
0H
0'
0)
0+
1#
0E
0M
0"
0.
0I
1A
0C
1,
1(
0J
0L
0>
1/
0-
1@
0B
10
0;
1=
0&
1%
#91000
1'
1"
1F
1H
1N
1L
0#
1E
1*
1)
0,
0G
0I
0A
1+
1-
0@
1D
1&
#92000
1#
0E
0G
1,
0)
1A
0C
0*
0H
0K
0M
0"
0'
0.
01
0F
0+
0(
1J
0L
0N
1<
0>
1/
09
12
0-
1@
0D
00
1;
0=
13
04
17
0&
0%
1$
#93000
1"
1'
1F
1H
1K
1M
0#
1E
1*
1)
0,
0G
0I
0A
1+
1-
0@
1D
1&
#94000
1"
0'
0#
1E
0G
1)
0*
0,
1H
0K
0M
0/
0F
0A
1C
1+
1(
0J
1L
0N
0<
1.
0-
1@
0D
10
0;
1?
0&
1%
#95000
0'
0N
0H
0*
0+
1#
0E
0G
0F
1I
0C
1,
1-
0@
1B
1&
#96000
1H
1+
1C
1'
1>
1)
0#
1E
1M
0"
11
0I
0,
0(
1J
0L
1.
19
02
0-
1@
0B
00
1;
0?
03
14
07
0&
0%
0$
#97000
0"
0K
0H
0*
0+
1#
0E
0G
0F
1I
0C
1,
1-
0@
1B
1&
#98000
0N
0*
0G
0H
0'
0)
0+
1#
0E
0M
0"
0.
0I
1A
0C
1,
1(
0J
0L
0>
1/
0-
1@
0B
10
0;
1=
0&
1%
#99000
1'
1"
1F
1H
1N
1L
0#
1E
1*
1)
0,
0G
0I
0A
1+
1-
0@
1D
1&
#100000
1#
0E
0G
1,
0)
1A
0C
0*
0H
0K
0M
0"
0'
0.
01
0F
0+
0(
1J
0L
0N
1<
0>
1/
09
12
0-
1@
0D
00
1;
0=
13
04
17
0&
0%
1$
